mcpy_compiler/__init__.py
mcpy_compiler/config.py
mcpy_compiler/mcpy_compiler.py
mcpy_compiler-0.5.0.dist-info/LICENSE
mcpy_compiler-0.5.0.dist-info/METADATA
mcpy_compiler-0.5.0.dist-info/WHEEL
mcpy_compiler-0.5.0.dist-info/top_level.txt
mcpy_compiler-0.5.0.dist-info/RECORD
