Metadata-Version: 2.1
Name: mcpy_compiler
Version: 0.5.0
Summary: A Minecraft bedrock addon compiler made in python
Author: Rose Kat
Project-URL: Homepage, https://github.com/RoseyKat/mcpy-compiler
Project-URL: Issues, https://github.com/RoseyKat/mcpy-compiler/issues
Classifier: Programming Language :: Python :: 3
Requires-Python: >=3.9
License-File: LICENSE
